setup.cfg
setup.py
pyprefixspan/__init__.py
pyprefixspan/pyprefixspan.py
pyprefixspan.egg-info/PKG-INFO
pyprefixspan.egg-info/SOURCES.txt
pyprefixspan.egg-info/dependency_links.txt
pyprefixspan.egg-info/top_level.txt