Metadata-Version: 1.1
Name: pyprefixspan
Version: 0.0.1
Summary: Python implementation for the algorithm PrefixSpan (Prefix-projected Sequential Pattern mining)
Home-page: https://github.com/takmanx/pyprefixspan
Author: Yukio TAKAHASHI
Author-email: takman@tuna.jpn.org
License: MIT License
Download-URL: https://github.com/takmanx/pyprefixspan
Keywords: prefixspan,sequence mining,data mining
Platform: UNKNOWN
Classifier: License :: OSI Approved :: MIT License
